{
    "default": [
        {
            "title": "Obtain the Sinner",
            "filename": "File:vo_dove_cacha_001.ogg",
            "text": "是需要人送信吗？……抱歉，我可能不是个好邮差，但如果大家不嫌弃的话，我很乐意帮忙传递心声。"
        },
        {
            "title": "Raise to Phase 1",
            "filename": "File:vo_dove_promotion_001.ogg",
            "text": "承载着大家心愿的信……我一定会尽快帮大家送到的。"
        },
        {
            "title": "Raise to Phase 3",
            "filename": "File:vo_dove_promotion2_001.ogg",
            "text": "拆信可是很有趣的哦，你要不要也试试？黑心、红心、碎掉的心……一把撕开，一览无余~"
        },
        {
            "title": "Level Start",
            "filename": "File:vo_dove_battlebegin_001.ogg",
            "text": "不用担心，我已经规划好路线了，跟紧我就好了哦。"
        },
        {
            "title": "Win Battles",
            "filename": "File:vo_dove_battlewin_001.ogg",
            "text": "诶呀，真是对不起~原来你们信中心愿的力量，也不过如此啊~"
        },
        {
            "title": "Lose Battles",
            "filename": "File:vo_dove_battlelose_001.ogg",
            "text": "对不起，对不起……我忘记信本身，有多脆弱了……"
        },
        {
            "title": "Ultimate Skill",
            "filename": "File:bt_dove_uniqueskill_001.ogg",
            "text": "信愿的力量会守护大家！"
        },
        {
            "title": "Die in Battles",
            "filename": "File:bt_dove_dead_001.ogg",
            "text": "不是说不会痛的吗……哈哈，又被骗了……"
        },
        {
            "title": "Greeting",
            "filename": "File:vo_dove_greeting_001.ogg",
            "text": "像局长这样的人，平时就算有烦恼也很难直接说出口吧……要不要试试写封信呢？有些话写在纸上，会更容易传达出去，也更容易被温柔接纳。这可是多芙的经验之谈哦~"
        },
        {
            "title": "Conversation 1",
            "filename": "File:vo_dove_talk1_001.ogg",
            "text": "来了这里我才知道，很多人都嫌寄信太慢了。确实，它不如点一下按钮就能发送的消息快捷，可是我相信，时间会带给它特别的温暖，那是墨水和纸的温度，是手掌和心脏的温度。"
        },
        {
            "title": "Conversation 2",
            "filename": "File:vo_dove_talk1_002.ogg",
            "text": "送信的活儿很辛苦吗？其实还好啦，毕竟小镇和管理局都不大，只比我之前住的村子大一点点。而且，我还有自行车，还有帮助我、相信我的大家。"
        },
        {
            "title": "Conversation 3",
            "filename": "File:vo_dove_talk1_003.ogg",
            "text": "其实，邮差并不像书里说的那样，一直是“派送幸福的人”。我也会送讣告、被退回的信，还有催缴账单……好在书里也说了，“无论被敲得多碎，生活都会尝试把自己粘起来的”。"
        },
        {
            "title": "Special Conversation 1",
            "filename": "File:vo_dove_talk2_001.ogg",
            "text": "以前，我从来不因为出不了门而觉得缺了点什么。我可以读书，通信，通过文字了解“外面的世界”。后来嘛……我发现书都是哄孩子的，信都是爸爸妈妈写的，“外面的世界”，也不过是一个更大的谎言。"
        },
        {
            "title": "Special Conversation 2",
            "filename": "File:vo_dove_talk2_002.ogg",
            "text": "你有交过笔友吗？有的话你就会知道，等待回信的时间，是最焦心又最幸福的。那是痛苦和幻灭无法打扰到的时间，也怪不得有人愿意蒙上双眼，永远生活在这段时间里。"
        },
        {
            "title": "Special Conversation 3",
            "filename": "File:vo_dove_talk2_003.ogg",
            "text": "来玩个小游戏吧，猜猜这些信里，哪几封真的是你的禁闭者写给你的？哈哈，对，就是这个表情！那么无奈，那么生动，我特别喜欢！"
        },
        {
            "title": "Full Compliance",
            "filename": "File:vo_dove_obeyfull_001.ogg",
            "text": "我总是不敢相信世上是存在像你这样的人的，是存在“真正传递和守护微小心愿的使者”的……或许这是上天对我欺骗别人的惩罚，用你的幻影哄骗我，然后让我重重摔落到地上……但没关系，至少在你消失之前，就让我这样相信吧……"
        },
        {
            "title": "Idle",
            "filename": "File:vo_dove_idle_001.ogg",
            "text": "“局长收”，嗯，然后再贴个爱心……你说等你醒了，能猜到这封“情书”，其实是邮差写的吗？"
        },
        {
            "title": "Annoyed",
            "filename": "File:vo_dove_clicking_001.ogg",
            "text": "别着急别着急，取信要排队才行哦……这么热切，还是说，你想要的不是信呢？"
        },
        {
            "title": "Special Attention",
            "filename": "File:vo_dove_specialattention_001.ogg",
            "text": "我记得书上说，两个人如果能对视十秒不移开视线，就说明他们很有缘分。局长如果想试试的话，多芙愿意帮忙~"
        },
        {
            "title": "Dispatch",
            "filename": "File:vo_dove_dispatch_001.ogg",
            "text": "今天也有好多信要送，可能会晚一点哦。"
        },
        {
            "title": "Dispatch Complete",
            "filename": "File:vo_dove_dispatch2_001.ogg",
            "text": "看着大家收到信后，表情那么幸福……连我也变得幸福起来了。"
        },
        {
            "title": "Level Up",
            "filename": "File:vo_dove_levelup_002.ogg",
            "text": "“变强”？我不太懂……意思是可以把幸福派送给更多的人吗？"
        },
        {
            "title": "Pat Head",
            "filename": "File:vo_dove_head_001.ogg",
            "text": ""
        },
        {
            "title": "Deploy",
            "filename": "File:bt_dove_jointeam_001.ogg",
            "text": ""
        }
    ]
}